lotrpy/__init__.py
lotrpy/lotr.py
lotrpy/models.py
lotrpy/serializers.py
lotrpy-1.0.1.dist-info/METADATA
lotrpy-1.0.1.dist-info/WHEEL
lotrpy-1.0.1.dist-info/licenses/LICENSE
lotrpy-1.0.1.dist-info/RECORD
