Metadata-Version: 2.1
Name: lotrpy
Version: 1.0.1
Summary: Lord Of the Rings Python SDK
License-File: LICENSE
Classifier: License :: OSI Approved :: MIT License
Classifier: Operating System :: OS Independent
Classifier: Programming Language :: Python :: 3
Requires-Python: >=3.10.6
Requires-Dist: requests
Provides-Extra: test
Requires-Dist: pytest; extra == 'test'
